<?xml version="1.0" encoding="utf-8" ?>
<hibernate-mapping xmlns="urn:nhibernate-mapping-2.2" assembly="MCT.DB.Entities" namespace="MCT.DB.Entities">
  <class name="AdditionalName" table="Names">
    
    <id name="Id" type="Int64" unsaved-value="0">
      <column name="Id" />
      <generator class="native" />
    </id>
    
    <!--foreign-key-->
    <many-to-one name="Node" class="MCT.DB.Entities.Node, MCT.DB.Entities" column="Node" cascade="all" not-null="true" />
    
    <!--//Name und Hierarchie-->
    <property name="Name" type="String"/>
    <property name="Language" type="String"/>
    <property name="IsPreferredName" type="Boolean"/>
  </class>
</hibernate-mapping>
